docs2txt/__init__.py
docs2txt/__main__.py
docs2txt/cli.py
docs2txt/docs_rs.py
docs2txt/utils.py
docs2txt-0.1.6.dist-info/AUTHORS.rst
docs2txt-0.1.6.dist-info/LICENSE
docs2txt-0.1.6.dist-info/METADATA
docs2txt-0.1.6.dist-info/WHEEL
docs2txt-0.1.6.dist-info/entry_points.txt
docs2txt-0.1.6.dist-info/top_level.txt
docs2txt-0.1.6.dist-info/RECORD
