Metadata-Version: 2.1
Name: docs2txt
Version: 0.1.6
Summary: A simple program to download documentation from docs.rs and convert it into a plaintext file.
Home-page: https://github.com/ehutzle/docs2txt
Author: Eric Richard
Author-email: ehutzle@gmail.com
License: MIT license
Keywords: docs2txt
Classifier: Development Status :: 2 - Pre-Alpha
Classifier: Intended Audience :: Developers
Classifier: License :: OSI Approved :: MIT License
Classifier: Natural Language :: English
Classifier: Programming Language :: Python :: 3
Classifier: Programming Language :: Python :: 3.6
Classifier: Programming Language :: Python :: 3.7
Classifier: Programming Language :: Python :: 3.8
Classifier: Programming Language :: Python :: 3.9
Classifier: Programming Language :: Python :: 3.10
Classifier: Programming Language :: Python :: 3.11
Requires-Python: >=3.6
License-File: LICENSE
License-File: AUTHORS.rst
